image_vectors/__init__.py
image_vectors/embedder.py
image_vectors-0.1.1.dist-info/METADATA
image_vectors-0.1.1.dist-info/WHEEL
image_vectors-0.1.1.dist-info/RECORD
